[
  {"transcription": "/kʌm/", "word": "come", "translation": "приходить", "type": "operations — 100 words"},
  {"transcription": "/get/", "word": "get", "translation": "получать", "type": "operations — 100 words"},
  {"transcription": "/giv/", "word": "give", "translation": "давать", "type": "operations — 100 words"},
  {"transcription": "/ɡəʊ/", "word": "go", "translation": "идти", "type": "operations — 100 words"},
  {"transcription": "/kiːp/", "word": "keep", "translation": "хранить", "type": "operations — 100 words"},
  {"transcription": "/let/", "word": "let", "translation": "позволять", "type": "operations — 100 words"},
  {"transcription": "/meɪk/", "word": "make", "translation": "делать", "type": "operations — 100 words"},
  {"transcription": "/pʊt/", "word": "put", "translation": "класть", "type": "operations — 100 words"},
  {"transcription": "/siːm/", "word": "seem", "translation": "казаться", "type": "operations — 100 words"},
  {"transcription": "/teɪk/", "word": "take", "translation": "брать", "type": "operations — 100 words"},
  {"transcription": "/biː/", "word": "be", "translation": "быть", "type": "operations — 100 words"},
  {"transcription": "/duː/", "word": "do", "translation": "делать", "type": "operations — 100 words"},
  {"transcription": "/hæv/", "word": "have", "translation": "иметь", "type": "operations — 100 words"},
  {"transcription": "/seɪ/", "word": "say", "translation": "говорить", "type": "operations — 100 words"},
  {"transcription": "/siː/", "word": "see", "translation": "видеть", "type": "operations — 100 words"},
  {"transcription": "/send/", "word": "send", "translation": "отправлять", "type": "operations — 100 words"},
  {"transcription": "/meɪ/", "word": "may", "translation": "может быть", "type": "operations — 100 words"},
  {"transcription": "/wɪl/", "word": "will", "translation": "вспом. гл. буд. времени", "type": "operations — 100 words"},
  {"transcription": "/əˈbaʊt/", "word": "about", "translation": "о, об", "type": "operations — 100 words"},
  {"transcription": "/əˈkrɒs/", "word": "across", "translation": "через", "type": "operations — 100 words"},
  {"transcription": "/ˈɑːftər/", "word": "after", "translation": "после", "type": "operations — 100 words"},
  {"transcription": "/əˈɡenst/", "word": "against", "translation": "против", "type": "operations — 100 words"},
  {"transcription": "/əˈmʌŋ/", "word": "among", "translation": "в, среди", "type": "operations — 100 words"},
  {"transcription": "/æt/", "word": "at", "translation": "в, на, у, за", "type": "operations — 100 words"},
  {"transcription": "/bɪˈfɔː/", "word": "before", "translation": "до, перед, раньше, прежде", "type": "operations — 100 words"},
  {"transcription": "/bɪˈtwiːn/", "word": "between", "translation": "между", "type": "operations — 100 words"},
  {"transcription": "/baɪ/", "word": "by", "translation": "указывает на деятеля, твор. падеж", "type": "operations — 100 words"},
  {"transcription": "/daʊn/", "word": "down", "translation": "вниз", "type": "operations — 100 words"},
  {"transcription": "/frɒm/", "word": "from", "translation": "от, с", "type": "operations — 100 words"},
  {"transcription": "/ɪn/", "word": "in", "translation": "в", "type": "operations — 100 words"},
  {"transcription": "/ɒf/", "word": "off", "translation": "удаление или отделение от чего—либо, от—, с—", "type": "operations — 100 words"},
  {"transcription": "/ɒn/", "word": "on", "translation": "на", "type": "operations — 100 words"},
  {"transcription": "/ˈəʊvə/", "word": "over", "translation": "над", "type": "operations — 100 words"},
  {"transcription": "/θruː/", "word": "through", "translation": "через, сквозь", "type": "operations — 100 words"},
  {"transcription": "/tə/", "word": "to", "translation": "к", "type": "operations — 100 words"},
  {"transcription": "/ˈʌndə/", "word": "under", "translation": "под", "type": "operations — 100 words"},
  {"transcription": "/ʌp/", "word": "up", "translation": "вверх", "type": "operations — 100 words"},
  {"transcription": "/wɪð/", "word": "with", "translation": "(вместе) с", "type": "operations — 100 words"},
  {"transcription": "/æz/", "word": "as", "translation": "так же как", "type": "operations — 100 words"},
  {"transcription": "/fɔː/", "word": "for", "translation": "для", "type": "operations — 100 words"},
  {"transcription": "/ɒv/", "word": "of", "translation": "принадлежность кому—либо/чему—либо, род. падеж", "type": "operations — 100 words"},
  {"transcription": "/tɪl/", "word": "till", "translation": "до", "type": "operations — 100 words"},
  {"transcription": "/ðæn/", "word": "than", "translation": "чем", "type": "operations — 100 words"},
  {"transcription": "/eɪ/", "word": "a", "translation": "неопределенный артикль", "type": "operations — 100 words"},
  {"transcription": "/ðiː/", "word": "the", "translation": "определенный артикль", "type": "operations — 100 words"},
  {"transcription": "/ɔːl/", "word": "all", "translation": "все, всё", "type": "operations — 100 words"},
  {"transcription": "/ˈeni/", "word": "any", "translation": "сколько—нибудь, нисколько, никто, ничто", "type": "operations — 100 words"},
  {"transcription": "/ˈevri/", "word": "every", "translation": "каждый", "type": "operations — 100 words"},
  {"transcription": "/nəʊ/", "word": "no", "translation": "никакой, нет", "type": "operations — 100 words"},
  {"transcription": "/ʌðə/", "word": "other", "translation": "другой", "type": "operations — 100 words"},
  {"transcription": "/sʌm/", "word": "some", "translation": "какое—то количество, немного, несколько", "type": "operations — 100 words"},
  {"transcription": "/sʌtʃ/", "word": "such", "translation": "такой, подобный", "type": "operations — 100 words"},
  {"transcription": "/ðæt/", "word": "that", "translation": "что, тот", "type": "operations — 100 words"},
  {"transcription": "/ðɪs/", "word": "this", "translation": "это", "type": "operations — 100 words"},
  {"transcription": "/aɪ/", "word": "i", "translation": "я", "type": "operations — 100 words"},
  {"transcription": "/hiː/", "word": "he", "translation": "он", "type": "operations — 100 words"},
  {"transcription": "/juː/", "word": "you", "translation": "вы, ты", "type": "operations — 100 words"},
  {"transcription": "/huː/", "word": "who", "translation": "кто", "type": "operations — 100 words"},
  {"transcription": "/ænd/", "word": "and", "translation": "и", "type": "operations — 100 words"},
  {"transcription": "/bɪˈkɒz/", "word": "because", "translation": "потому что", "type": "operations — 100 words"},
  {"transcription": "/bʌt/", "word": "but", "translation": "но", "type": "operations — 100 words"},
  {"transcription": "/ɔː/", "word": "or", "translation": "или", "type": "operations — 100 words"},
  {"transcription": "/ɪf/", "word": "if", "translation": "если", "type": "operations — 100 words"},
  {"transcription": "/ðəʊ/", "word": "though", "translation": "несмотря на, хотя", "type": "operations — 100 words"},
  {"transcription": "/waɪl/", "word": "while", "translation": "в то время как, пока, когда", "type": "operations — 100 words"},
  {"transcription": "/haʊ/", "word": "how", "translation": "как", "type": "operations — 100 words"},
  {"transcription": "/wen/", "word": "when", "translation": "когда", "type": "operations — 100 words"},
  {"transcription": "/weə/", "word": "where", "translation": "где", "type": "operations — 100 words"},
  {"transcription": "/waɪ/", "word": "why", "translation": "почему", "type": "operations — 100 words"},
  {"transcription": "/əˈɡen/", "word": "again", "translation": "опять", "type": "operations — 100 words"},
  {"transcription": "/ˈevə/", "word": "ever", "translation": "когда—либо", "type": "operations — 100 words"},
  {"transcription": "/fɑː/", "word": "far", "translation": "далеко", "type": "operations — 100 words"},
  {"transcription": "/ˈfɔːwəd/", "word": "forward", "translation": "вперед", "type": "operations — 100 words"},
  {"transcription": "/hɪə/", "word": "here", "translation": "здесь, сюда", "type": "operations — 100 words"},
  {"transcription": "/nɪə/", "word": "near", "translation": "близко, около, поблизости", "type": "operations — 100 words"},
  {"transcription": "/naʊ/", "word": "now", "translation": "теперь, сейчас", "type": "operations — 100 words"},
  {"transcription": "/aʊt/", "word": "out", "translation": "вне, из", "type": "operations — 100 words"},
  {"transcription": "/stɪl/", "word": "still", "translation": "все еще", "type": "operations — 100 words"},
  {"transcription": "/ðen/", "word": "then", "translation": "тогда, потом", "type": "operations — 100 words"},
  {"transcription": "/ðeə/", "word": "there", "translation": "там, туда", "type": "operations — 100 words"},
  {"transcription": "/təˈɡeðə/", "word": "together", "translation": "вместе", "type": "operations — 100 words"},
  {"transcription": "/wel/", "word": "well", "translation": "хорошо, вполне", "type": "operations — 100 words"},
  {"transcription": "/ˈɔːlməʊst/", "word": "almost", "translation": "почти", "type": "operations — 100 words"},
  {"transcription": "/ɪˈnʌf/", "word": "enough", "translation": "достаточно", "type": "operations — 100 words"},
  {"transcription": "/ˈiːvən/", "word": "even", "translation": "даже", "type": "operations — 100 words"},
  {"transcription": "/ˈlɪtl/", "word": "little", "translation": "маленький", "type": "operations — 100 words"},
  {"transcription": "/mʌtʃ/", "word": "much", "translation": "много, сколько", "type": "operations — 100 words"},
  {"transcription": "/nɒt/", "word": "not", "translation": "не", "type": "operations — 100 words"},
  {"transcription": "/ˈəʊnli/", "word": "only", "translation": "только, всего лишь", "type": "operations — 100 words"},
  {"transcription": "/kwaɪt/", "word": "quite", "translation": "довольно", "type": "operations — 100 words"},
  {"transcription": "/səʊ/", "word": "so", "translation": "так, настолько, таким образом", "type": "operations — 100 words"},
  {"transcription": "/ˈveri/", "word": "very", "translation": "очень", "type": "operations — 100 words"},
  {"transcription": "/təˈmɒrəʊ/", "word": "tomorrow", "translation": "завтра", "type": "operations — 100 words"},
  {"transcription": "/ˈjestədeɪ/", "word": "yesterday", "translation": "вчера", "type": "operations — 100 words"},
  {"transcription": "/nɔːθ/", "word": "north", "translation": "север", "type": "operations — 100 words"},
  {"transcription": "/saʊθ/", "word": "south", "translation": "юг", "type": "operations — 100 words"},
  {"transcription": "/iːst/", "word": "east", "translation": "восток", "type": "operations — 100 words"},
  {"transcription": "/west/", "word": "west", "translation": "запад", "type": "operations — 100 words"},
  {"transcription": "/pliːz/", "word": "please", "translation": "пожалуйста", "type": "operations — 100 words"},
  {"transcription": "/jes/", "word": "yes", "translation": "да", "type": "operations — 100 words"},

  {"transcription": "/ˈæŋɡl/", "word": "angle", "translation": "угол", "type": "things — 200 words"},
  {"transcription": "/ænt/", "word": "ant", "translation": "муравей", "type": "things — 200 words"},
  {"transcription": "/ˈæpl/", "word": "apple", "translation": "яблоко", "type": "things — 200 words"},
  {"transcription": "/ɑːtʃ/", "word": "arch", "translation": "арка", "type": "things — 200 words"},
  {"transcription": "/ɑːm/", "word": "arm", "translation": "рука", "type": "things — 200 words"},
  {"transcription": "/ˈɑːmi/", "word": "army", "translation": "армия", "type": "things — 200 words"},
  {"transcription": "/ˈbeɪbi/", "word": "baby", "translation": "малыш", "type": "things — 200 words"},
  {"transcription": "/bæɡ/", "word": "bag", "translation": "сумка", "type": "things — 200 words"},
  {"transcription": "/bɔːl/", "word": "ball", "translation": "мяч", "type": "things — 200 words"},
  {"transcription": "/bænd/", "word": "band", "translation": "группа", "type": "things — 200 words"},
  {"transcription": "/ˈbeɪsən/", "word": "basin", "translation": "миска, таз", "type": "things — 200 words"},
  {"transcription": "/ˈbɑːskɪt/", "word": "basket", "translation": "корзина", "type": "things — 200 words"},
  {"transcription": "/bɑːθ/", "word": "bath", "translation": "ванна", "type": "things — 200 words"},
  {"transcription": "/bed/", "word": "bed", "translation": "кровать", "type": "things — 200 words"},
  {"transcription": "/biː/", "word": "bee", "translation": "пчела", "type": "things — 200 words"},
  {"transcription": "/bel/", "word": "bell", "translation": "колокол", "type": "things — 200 words"},
  {"transcription": "/ˈberi/", "word": "berry", "translation": "ягода", "type": "things — 200 words"},
  {"transcription": "/bɜːd/", "word": "bird", "translation": "птица", "type": "things — 200 words"},
  {"transcription": "/bleɪd/", "word": "blade", "translation": "лезвие", "type": "things — 200 words"},
  {"transcription": "/bɔːd/", "word": "board", "translation": "доска", "type": "things — 200 words"},
  {"transcription": "/bəʊt/", "word": "boat", "translation": "лодка", "type": "things — 200 words"},
  {"transcription": "/bəʊn/", "word": "bone", "translation": "кость", "type": "things — 200 words"},
  {"transcription": "/bʊk/", "word": "book", "translation": "книга", "type": "things — 200 words"},
  {"transcription": "/buːt/", "word": "boot", "translation": "сапог", "type": "things — 200 words"},
  {"transcription": "/ˈbɒtl/", "word": "bottle", "translation": "бутылка", "type": "things — 200 words"},
  {"transcription": "/bɒks/", "word": "box", "translation": "коробка", "type": "things — 200 words"},
  {"transcription": "/bɔɪ/", "word": "boy", "translation": "мальчик", "type": "things — 200 words"},
  {"transcription": "/breɪn/", "word": "brain", "translation": "мозг", "type": "things — 200 words"},
  {"transcription": "/breɪk/", "word": "brake", "translation": "тормоз", "type": "things — 200 words"},
  {"transcription": "/brɑːnʃ/", "word": "branch", "translation": "ветка", "type": "things — 200 words"},
  {"transcription": "/brɪk/", "word": "brick", "translation": "кирпич", "type": "things — 200 words"},
  {"transcription": "/brɪdʒ/", "word": "bridge", "translation": "мост", "type": "things — 200 words"},
  {"transcription": "/brʌʃ/", "word": "brush", "translation": "щётка", "type": "things — 200 words"},
  {"transcription": "/ˈbʌkɪt/", "word": "bucket", "translation": "ведро", "type": "things — 200 words"},
  {"transcription": "/bʌlb/", "word": "bulb", "translation": "лампочка", "type": "things — 200 words"},
  {"transcription": "/ˈbʌtən/", "word": "button", "translation": "кнопка", "type": "things — 200 words"},
  {"transcription": "/keɪk/", "word": "cake", "translation": "пирог", "type": "things — 200 words"},
  {"transcription": "/ˈkæmərə/", "word": "camera", "translation": "фотоаппарат", "type": "things — 200 words"},
  {"transcription": "/kɑːd/", "word": "card", "translation": "карточка", "type": "things — 200 words"},
  {"transcription": "/kɑːt/", "word": "cart", "translation": "тележка", "type": "things — 200 words"},
  {"transcription": "/ˈkærɪdʒ/", "word": "carriage", "translation": "вагон", "type": "things — 200 words"},
  {"transcription": "/kæt/", "word": "cat", "translation": "кошка", "type": "things — 200 words"},
  {"transcription": "/tʃeɪn/", "word": "chain", "translation": "цепь", "type": "things — 200 words"},
  {"transcription": "/tʃiːz/", "word": "cheese", "translation": "сыр", "type": "things — 200 words"},
  {"transcription": "/tʃest/", "word": "chest", "translation": "грудь", "type": "things — 200 words"},
  {"transcription": "/tʃɪn/", "word": "chin", "translation": "подбородок", "type": "things — 200 words"},
  {"transcription": "/tʃɜːtʃ/", "word": "church", "translation": "церковь", "type": "things — 200 words"},
  {"transcription": "/ˈsɜːkl/", "word": "circle", "translation": "круг", "type": "things — 200 words"},
  {"transcription": "/klɒk/", "word": "clock", "translation": "часы", "type": "things — 200 words"},
  {"transcription": "/klaʊd/", "word": "cloud", "translation": "облако", "type": "things — 200 words"},
  {"transcription": "/kəʊt/", "word": "coat", "translation": "пальто", "type": "things — 200 words"},
  {"transcription": "/ˈkɒlə/", "word": "collar", "translation": "воротник", "type": "things — 200 words"},
  {"transcription": "/kəʊm/", "word": "comb", "translation": "расческа", "type": "things — 200 words"},
  {"transcription": "/kɔːd/", "word": "cord", "translation": "провод", "type": "things — 200 words"},
  {"transcription": "/kaʊ/", "word": "cow", "translation": "корова", "type": "things — 200 words"},
  {"transcription": "/kʌp/", "word": "cup", "translation": "чашка", "type": "things — 200 words"},
  {"transcription": "/ˈkɜːtən/", "word": "curtain", "translation": "занавеска", "type": "things — 200 words"},
  {"transcription": "/ˈkʊʃən/", "word": "cushion", "translation": "подушка", "type": "things — 200 words"},
  {"transcription": "/dɒɡ/", "word": "dog", "translation": "собака", "type": "things — 200 words"},
  {"transcription": "/dɔː/", "word": "door", "translation": "дверь", "type": "things — 200 words"},
  {"transcription": "/dreɪn/", "word": "drain", "translation": "водосток", "type": "things — 200 words"},
  {"transcription": "/drɔː/", "word": "drawer", "translation": "выдвижной ящик", "type": "things — 200 words"},
  {"transcription": "/dres/", "word": "dress", "translation": "платье", "type": "things — 200 words"},
  {"transcription": "/drɒp/", "word": "drop", "translation": "капля", "type": "things — 200 words"},
  {"transcription": "/ɪə/", "word": "ear", "translation": "ухо", "type": "things — 200 words"},
  {"transcription": "/eɡ/", "word": "egg", "translation": "яйцо", "type": "things — 200 words"},
  {"transcription": "/ˈendʒɪn/", "word": "engine", "translation": "двигатель", "type": "things — 200 words"},
  {"transcription": "/aɪ/", "word": "eye", "translation": "глаз", "type": "things — 200 words"},
  {"transcription": "/feɪs/", "word": "face", "translation": "лицо", "type": "things — 200 words"},
  {"transcription": "/fɑːm/", "word": "farm", "translation": "ферма", "type": "things — 200 words"},
  {"transcription": "/ˈfeðə/", "word": "feather", "translation": "перо", "type": "things — 200 words"},
  {"transcription": "/ˈfɪŋɡə/", "word": "finger", "translation": "палец", "type": "things — 200 words"},
  {"transcription": "/fɪʃ/", "word": "fish", "translation": "рыба", "type": "things — 200 words"},
  {"transcription": "/flæɡ/", "word": "flag", "translation": "флаг", "type": "things — 200 words"},
  {"transcription": "/flɔː/", "word": "floor", "translation": "пол, этаж", "type": "things — 200 words"},
  {"transcription": "/flaɪ/", "word": "fly", "translation": "муха", "type": "things — 200 words"},
  {"transcription": "/fʊt/", "word": "foot", "translation": "ступня", "type": "things — 200 words"},
  {"transcription": "/fɔːk/", "word": "fork", "translation": "вилка", "type": "things — 200 words"},
  {"transcription": "/faʊl/", "word": "fowl", "translation": "домашняя птица", "type": "things — 200 words"},
  {"transcription": "/freɪm/", "word": "frame", "translation": "рамка", "type": "things — 200 words"},
  {"transcription": "/ˈɡɑːdən/", "word": "garden", "translation": "сад", "type": "things — 200 words"},
  {"transcription": "/ɡɜːl/", "word": "girl", "translation": "девочка", "type": "things — 200 words"},
  {"transcription": "/ɡlʌv/", "word": "glove", "translation": "перчатка", "type": "things — 200 words"},
  {"transcription": "/ɡəʊt/", "word": "goat", "translation": "козел", "type": "things — 200 words"},
  {"transcription": "/ɡʌn/", "word": "gun", "translation": "огнестрельное оружие", "type": "things — 200 words"},
  {"transcription": "/heə/", "word": "hair", "translation": "волосы", "type": "things — 200 words"},
  {"transcription": "/ˈhæmə/", "word": "hammer", "translation": "молоток", "type": "things — 200 words"},
  {"transcription": "/hænd/", "word": "hand", "translation": "рука", "type": "things — 200 words"},
  {"transcription": "/hæt/", "word": "hat", "translation": "шляпа", "type": "things — 200 words"},
  {"transcription": "/hed/", "word": "head", "translation": "голова", "type": "things — 200 words"},
  {"transcription": "/hɑːt/", "word": "heart", "translation": "сердце", "type": "things — 200 words"},
  {"transcription": "/hʊk/", "word": "hook", "translation": "крючок", "type": "things — 200 words"},
  {"transcription": "/hɔːn/", "word": "horn", "translation": "рог", "type": "things — 200 words"},
  {"transcription": "/hɔːs/", "word": "horse", "translation": "лошадь", "type": "things — 200 words"},
  {"transcription": "/ˈhɒspɪtəl/", "word": "hospital", "translation": "больница", "type": "things — 200 words"},
  {"transcription": "/haʊs/", "word": "house", "translation": "дом", "type": "things — 200 words"},
  {"transcription": "/ˈaɪlənd/", "word": "island", "translation": "остров", "type": "things — 200 words"},
  {"transcription": "/ˈdʒuːəl/", "word": "jewel", "translation": "драгоценный камень", "type": "things — 200 words"},
  {"transcription": "/ˈketl/", "word": "kettle", "translation": "чайник", "type": "things — 200 words"},
  {"transcription": "/kiː/", "word": "key", "translation": "ключ", "type": "things — 200 words"},

  {"transcription": "/niː/", "word": "knee", "translation": "колено", "type": "things — 200 words"},
  {"transcription": "/naɪf/", "word": "knife", "translation": "нож", "type": "things — 200 words"},
  {"transcription": "/nɒt/", "word": "knot", "translation": "узел", "type": "things — 200 words"},
  {"transcription": "/liːf/", "word": "leaf", "translation": "лист", "type": "things — 200 words"},
  {"transcription": "/leɡ/", "word": "leg", "translation": "нога", "type": "things — 200 words"},
  {"transcription": "/ˈlaɪbrəri/", "word": "library", "translation": "библиотека", "type": "things — 200 words"},
  {"transcription": "/laɪn/", "word": "line", "translation": "линия", "type": "things — 200 words"},
  {"transcription": "/lɪp/", "word": "lip", "translation": "губа", "type": "things — 200 words"},
  {"transcription": "/lɒk/", "word": "lock", "translation": "замок", "type": "things — 200 words"},
  {"transcription": "/mæp/", "word": "map", "translation": "карта", "type": "things — 200 words"},

  {"transcription": "/mætʃ/", "word": "match", "translation": "состязание", "type": "things — 200 words"},
  {"transcription": "/ˈmʌŋki/", "word": "monkey", "translation": "обезьяна", "type": "things — 200 words"},
  {"transcription": "/muːn/", "word": "moon", "translation": "луна", "type": "things — 200 words"},
  {"transcription": "/maʊθ/", "word": "mouth", "translation": "рот", "type": "things — 200 words"},
  {"transcription": "/ˈmʌsl/", "word": "muscle", "translation": "мышца", "type": "things — 200 words"},
  {"transcription": "/neɪl/", "word": "nail", "translation": "гвоздь, ногть", "type": "things — 200 words"},
  {"transcription": "/nek/", "word": "neck", "translation": "шея", "type": "things — 200 words"},
  {"transcription": "/ˈniːdl/", "word": "needle", "translation": "игла", "type": "things — 200 words"},
  {"transcription": "/nɜːv/", "word": "nerve", "translation": "нерв", "type": "things — 200 words"},
  {"transcription": "/net/", "word": "net", "translation": "сеть", "type": "things — 200 words"},

  {"transcription": "/kiː/", "word": "key", "translation": "ключ", "type": "things — 200 words"},
  {"transcription": "/kiː/", "word": "key", "translation": "ключ", "type": "things — 200 words"},
  {"transcription": "/kiː/", "word": "key", "translation": "ключ", "type": "things — 200 words"},
  {"transcription": "/kiː/", "word": "key", "translation": "ключ", "type": "things — 200 words"},
  {"transcription": "/kiː/", "word": "key", "translation": "ключ", "type": "things — 200 words"},
  {"transcription": "/kiː/", "word": "key", "translation": "ключ", "type": "things — 200 words"},
  {"transcription": "/kiː/", "word": "key", "translation": "ключ", "type": "things — 200 words"},
  {"transcription": "/kiː/", "word": "key", "translation": "ключ", "type": "things — 200 words"},
  {"transcription": "/kiː/", "word": "key", "translation": "ключ", "type": "things — 200 words"},
  {"transcription": "/kiː/", "word": "key", "translation": "ключ", "type": "things — 200 words"},

  {"transcription": "/kiː/", "word": "key", "translation": "ключ", "type": "things — 200 words"},
  {"transcription": "/kiː/", "word": "key", "translation": "ключ", "type": "things — 200 words"},
  {"transcription": "/kiː/", "word": "key", "translation": "ключ", "type": "things — 200 words"},
  {"transcription": "/kiː/", "word": "key", "translation": "ключ", "type": "things — 200 words"},
  {"transcription": "/kiː/", "word": "key", "translation": "ключ", "type": "things — 200 words"},
  {"transcription": "/kiː/", "word": "key", "translation": "ключ", "type": "things — 200 words"},
  {"transcription": "/kiː/", "word": "key", "translation": "ключ", "type": "things — 200 words"},
  {"transcription": "/kiː/", "word": "key", "translation": "ключ", "type": "things — 200 words"},
  {"transcription": "/kiː/", "word": "key", "translation": "ключ", "type": "things — 200 words"},
  {"transcription": "/kiː/", "word": "key", "translation": "ключ", "type": "things — 200 words"},

  {"transcription": "/kiː/", "word": "key", "translation": "ключ", "type": "things — 200 words"},
  {"transcription": "/kiː/", "word": "key", "translation": "ключ", "type": "things — 200 words"},
  {"transcription": "/kiː/", "word": "key", "translation": "ключ", "type": "things — 200 words"},
  {"transcription": "/kiː/", "word": "key", "translation": "ключ", "type": "things — 200 words"},
  {"transcription": "/kiː/", "word": "key", "translation": "ключ", "type": "things — 200 words"},
  {"transcription": "/kiː/", "word": "key", "translation": "ключ", "type": "things — 200 words"},
  {"transcription": "/kiː/", "word": "key", "translation": "ключ", "type": "things — 200 words"},
  {"transcription": "/kiː/", "word": "key", "translation": "ключ", "type": "things — 200 words"},
  {"transcription": "/kiː/", "word": "key", "translation": "ключ", "type": "things — 200 words"},
  {"transcription": "/kiː/", "word": "key", "translation": "ключ", "type": "things — 200 words"}

]
